mack/__init__.py
mack-0.5.0.dist-info/LICENSE
mack-0.5.0.dist-info/METADATA
mack-0.5.0.dist-info/WHEEL
mack-0.5.0.dist-info/RECORD
