Metadata-Version: 2.1
Name: mack
Version: 0.5.0
Summary: 
Author: Matthew Powers
Author-email: matthewkevinpowers@gmail.com
Requires-Python: >=3.9,<4.0
Classifier: Programming Language :: Python :: 3
Classifier: Programming Language :: Python :: 3.9
Classifier: Programming Language :: Python :: 3.10
Classifier: Programming Language :: Python :: 3.11
